alma_hilse/__init__.py
alma_hilse/__main__.py
alma_hilse/cli/__init__.py
alma_hilse/cli/corr.py
alma_hilse/cli/timing.py
alma_hilse/cli/utils.py
alma_hilse/lib/__init__.py
alma_hilse/lib/corr/__init__.py
alma_hilse/lib/corr/drx.py
alma_hilse/lib/lo_timing/__init__.py
alma_hilse/lib/lo_timing/lftrr.py
alma_hilse/lib/utils/__init__.py
alma_hilse/lib/utils/initCCL_HIL.py
alma_hilse-0.3.2.dist-info/LICENSE
alma_hilse-0.3.2.dist-info/METADATA
alma_hilse-0.3.2.dist-info/WHEEL
alma_hilse-0.3.2.dist-info/entry_points.txt
alma_hilse-0.3.2.dist-info/top_level.txt
alma_hilse-0.3.2.dist-info/RECORD
