Metadata-Version: 2.1
Name: alma-hilse
Version: 0.3.2
Summary: ALMA Hardware-In-the-Loop Simulation Environment setup, monitoring and verification package
Home-page: https://bitbucket.sco.alma.cl/projects/ESG/repos/alma-hilse
Author: Jose L. Ortiz / ADE
Author-email: jose.ortiz@alma.cl
License: MIT
Platform: UNKNOWN
Classifier: Programming Language :: Python :: 3
Classifier: License :: OSI Approved :: MIT License
Classifier: Operating System :: OS Independent
License-File: LICENSE
Requires-Dist: click (==8.0.4)
Requires-Dist: typer (==0.4.0)
Requires-Dist: rich (==12.0.0)
Provides-Extra: test
Requires-Dist: pytest ; extra == 'test'
